get_chaining.py
flake8_get_chaining-0.2.0.dist-info/LICENSE
flake8_get_chaining-0.2.0.dist-info/METADATA
flake8_get_chaining-0.2.0.dist-info/WHEEL
flake8_get_chaining-0.2.0.dist-info/entry_points.txt
flake8_get_chaining-0.2.0.dist-info/top_level.txt
flake8_get_chaining-0.2.0.dist-info/RECORD
