Metadata-Version: 2.1
Name: flake8-get-chaining
Version: 0.2.0
Summary: A plugin for flake8 finding likely bugs when chaining dict.get calls
Author-email: Augustin Bouverot <augustin.bouverot@gmail.com>
License: MIT
Project-URL: Homepage, https://github.com/Sacrimento/flake8-get-chaining
Project-URL: Change Log, https://github.com/Sacrimento/flake8-get-chaining#change-log
Keywords: flake8,get-chaining,bugs,pyflakes,pylint,linter,qa
Classifier: Development Status :: 4 - Beta
Classifier: Environment :: Console
Classifier: Framework :: Flake8
Classifier: Intended Audience :: Developers
Classifier: License :: OSI Approved :: MIT License
Classifier: Operating System :: OS Independent
Classifier: Programming Language :: Python
Classifier: Programming Language :: Python :: 3
Classifier: Programming Language :: Python :: 3.7
Classifier: Programming Language :: Python :: 3.8
Classifier: Programming Language :: Python :: 3.9
Classifier: Programming Language :: Python :: 3.10
Classifier: Programming Language :: Python :: 3.11
Classifier: Programming Language :: Python :: 3 :: Only
Classifier: Topic :: Software Development :: Libraries :: Python Modules
Classifier: Topic :: Software Development :: Quality Assurance
Requires-Python: >=3.7
License-File: LICENSE
Requires-Dist: flake8 (>=3.0.0)
Provides-Extra: dev
Requires-Dist: tox ; extra == 'dev'
Requires-Dist: pytest ; extra == 'dev'
Requires-Dist: coverage ; extra == 'dev'
Requires-Dist: pylint ; extra == 'dev'
Requires-Dist: isort ; extra == 'dev'
Requires-Dist: mypy ; extra == 'dev'
